README.rst
setup.cfg
setup.py
py_task_scheduler.egg-info/PKG-INFO
py_task_scheduler.egg-info/SOURCES.txt
py_task_scheduler.egg-info/dependency_links.txt
py_task_scheduler.egg-info/entry_points.txt
py_task_scheduler.egg-info/not-zip-safe
py_task_scheduler.egg-info/requires.txt
py_task_scheduler.egg-info/top_level.txt
taskscheduler/__init__.py
taskscheduler/taskscheduler.py