Metadata-Version: 1.1
Name: py-task-scheduler
Version: 0.0.2
Summary: A tool to help you schedule your task according to your config file
Home-page: https://github.com/tzutalin/task-scheduler
Author: TzuTa Lin
Author-email: tzu.ta.lin@gmail.com
License: MIT license
Keywords: taskscheduler
Platform: UNKNOWN
Classifier: Development Status :: 2 - Pre-Alpha
Classifier: Intended Audience :: Developers
Classifier: License :: OSI Approved :: MIT License
Classifier: Natural Language :: English
Classifier: Programming Language :: Python :: 2
Classifier: Programming Language :: Python :: 2.6
Classifier: Programming Language :: Python :: 2.7
Classifier: Programming Language :: Python :: 3
Classifier: Programming Language :: Python :: 3.3
Classifier: Programming Language :: Python :: 3.4
Classifier: Programming Language :: Python :: 3.5
Classifier: Programming Language :: Python :: 3.6
